bvx_docker/__init__.py
bvx_docker/container_exists.py
bvx_docker/network_exists.py
bvx_docker-0.0.9.dist-info/LICENSE
bvx_docker-0.0.9.dist-info/METADATA
bvx_docker-0.0.9.dist-info/WHEEL
bvx_docker-0.0.9.dist-info/top_level.txt
bvx_docker-0.0.9.dist-info/RECORD
