Metadata-Version: 2.1
Name: bvx-docker
Version: 0.0.9
Summary: docker helpers.
Home-page: https://github.com/kotsutsumi/bvx-docker
Author: Kazuhiro Kotsutsumi
License: The MIT License
Platform: UNKNOWN
License-File: LICENSE
Requires-Dist: docker (~=5.0.3)
